[
  {
    "distance_map": {
      "0": 1.7976931348623157e+308,
      "1": 0,
      "2": 1.7976931348623157e+308,
      "3": 1.7976931348623157e+308,
      "4": 1.7976931348623157e+308
    },
    "timestamp": 0
  },
  {
    "distance_map": {
      "0": 1.7976931348623157e+308,
      "1": 0,
      "2": 1.7976931348623157e+308,
      "3": 1.7976931348623157e+308,
      "4": 1.7976931348623157e+308
    },
    "timestamp": 1
  },
  {
    "distance_map": {
      "0": 1.7976931348623157e+308,
      "1": 0,
      "2": 1.7976931348623157e+308,
      "3": 1.7976931348623157e+308,
      "4": 1.7976931348623157e+308
    },
    "timestamp": 2
  },
  {
    "distance_map": {
      "0": 1.7976931348623157e+308,
      "1": 0,
      "2": 1.7976931348623157e+308,
      "3": 1.7976931348623157e+308,
      "4": 1.7976931348623157e+308
    },
    "timestamp": 3
  },
  {
    "distance_map": {
      "0": 1.7976931348623157e+308,
      "1": 0,
      "2": 1.7976931348623157e+308,
      "3": 1.7976931348623157e+308,
      "4": 1.7976931348623157e+308
    },
    "timestamp": 4
  },
  {
    "distance_map": {
      "0": 1.7976931348623157e+308,
      "1": 0,
      "2": 1.7976931348623157e+308,
      "3": 1.7976931348623157e+308,
      "4": 1.7976931348623157e+308
    },
    "timestamp": 5
  },
  {
    "distance_map": {
      "0": 2,
      "1": 0,
      "2": 1.7976931348623157e+308,
      "3": 1.7976931348623157e+308,
      "4": 1
    },
    "timestamp": 6
  },
  {
    "distance_map": {
      "0": 2,
      "1": 0,
      "2": 3,
      "3": 2,
      "4": 1
    },
    "timestamp": 7
  },
  {
    "distance_map": {
      "0": 2,
      "1": 0,
      "2": 3,
      "3": 2,
      "4": 1
    },
    "timestamp": 8
  },
  {
    "distance_map": {
      "0": 2,
      "1": 0,
      "2": 1.7976931348623157e+308,
      "3": 2,
      "4": 1
    },
    "timestamp": 9
  },
  {
    "distance_map": {
      "0": 2,
      "1": 0,
      "2": 1.7976931348623157e+308,
      "3": 2,
      "4": 1
    },
    "timestamp": 10
  },
  {
    "distance_map": {
      "0": 1.7976931348623157e+308,
      "1": 0,
      "2": 1.7976931348623157e+308,
      "3": 1.7976931348623157e+308,
      "4": 1.7976931348623157e+308
    },
    "timestamp": 11
  },
  {
    "distance_map": {
      "0": 1.7976931348623157e+308,
      "1": 0,
      "2": 1.7976931348623157e+308,
      "3": 1.7976931348623157e+308,
      "4": 1.7976931348623157e+308
    },
    "timestamp": 12
  },
  {
    "distance_map": {
      "0": 1.7976931348623157e+308,
      "1": 0,
      "2": 1.7976931348623157e+308,
      "3": 1.7976931348623157e+308,
      "4": 1.7976931348623157e+308
    },
    "timestamp": 13
  },
  {
    "distance_map": {
      "0": 1.7976931348623157e+308,
      "1": 0,
      "2": 1.7976931348623157e+308,
      "3": 1.7976931348623157e+308,
      "4": 1.7976931348623157e+308
    },
    "timestamp": 14
  },
  {
    "distance_map": {
      "0": 1,
      "1": 0,
      "2": 2,
      "3": 3,
      "4": 3
    },
    "timestamp": 15
  },
  {
    "distance_map": {
      "0": 1,
      "1": 0,
      "2": 2,
      "3": 3,
      "4": 3
    },
    "timestamp": 16
  },
  {
    "distance_map": {
      "0": 1,
      "1": 0,
      "2": 1,
      "3": 2,
      "4": 2
    },
    "timestamp": 17
  },
  {
    "distance_map": {
      "0": 1,
      "1": 0,
      "2": 1,
      "3": 2,
      "4": 3
    },
    "timestamp": 18
  },
  {
    "distance_map": {
      "0": 1,
      "1": 0,
      "2": 2,
      "3": 3,
      "4": 4
    },
    "timestamp": 19
  },
  {
    "distance_map": {
      "0": 1,
      "1": 0,
      "2": 2,
      "3": 1,
      "4": 2
    },
    "timestamp": 20
  },
  {
    "distance_map": {
      "0": 1,
      "1": 0,
      "2": 2,
      "3": 1,
      "4": 2
    },
    "timestamp": 21
  },
  {
    "distance_map": {
      "0": 1,
      "1": 0,
      "2": 2,
      "3": 1,
      "4": 2
    },
    "timestamp": 22
  },
  {
    "distance_map": {
      "0": 1,
      "1": 0,
      "2": 2,
      "3": 1,
      "4": 2
    },
    "timestamp": 23
  },
  {
    "distance_map": {
      "0": 1,
      "1": 0,
      "2": 2,
      "3": 1,
      "4": 2
    },
    "timestamp": 24
  }
]